dracox/__init__.py
dracox/dracox_ext.cpython-310-darwin.so
bin/draco_encoder
bin/draco_decoder-1.5.7
bin/draco_decoder
bin/draco_encoder-1.5.7
include/draco/draco_features.h
include/draco/mesh/mesh_cleanup.h
include/draco/mesh/mesh_are_equivalent.h
include/draco/mesh/triangle_soup_mesh_builder.h
include/draco/mesh/corner_table_iterators.h
include/draco/mesh/mesh.h
include/draco/mesh/mesh_indices.h
include/draco/mesh/mesh_attribute_corner_table.h
include/draco/mesh/valence_cache.h
include/draco/mesh/mesh_stripifier.h
include/draco/mesh/mesh_misc_functions.h
include/draco/mesh/corner_table.h
include/draco/mesh/mesh_features.h
include/draco/point_cloud/point_cloud.h
include/draco/point_cloud/point_cloud_builder.h
include/draco/core/vector_d.h
include/draco/core/bit_utils.h
include/draco/core/status.h
include/draco/core/divide.h
include/draco/core/encoder_buffer.h
include/draco/core/quantization_utils.h
include/draco/core/draco_types.h
include/draco/core/options.h
include/draco/core/data_buffer.h
include/draco/core/draco_index_type.h
include/draco/core/constants.h
include/draco/core/status_or.h
include/draco/core/math_utils.h
include/draco/core/macros.h
include/draco/core/draco_version.h
include/draco/core/varint_encoding.h
include/draco/core/hash_utils.h
include/draco/core/draco_index_type_vector.h
include/draco/core/varint_decoding.h
include/draco/core/decoder_buffer.h
include/draco/core/bounding_box.h
include/draco/core/cycle_timer.h
include/draco/io/parser_utils.h
include/draco/io/file_utils.h
include/draco/io/ply_property_writer.h
include/draco/io/stdio_file_reader.h
include/draco/io/file_reader_interface.h
include/draco/io/point_cloud_io.h
include/draco/io/stl_decoder.h
include/draco/io/obj_decoder.h
include/draco/io/file_writer_utils.h
include/draco/io/ply_encoder.h
include/draco/io/file_writer_interface.h
include/draco/io/ply_reader.h
include/draco/io/mesh_io.h
include/draco/io/ply_property_reader.h
dracox-0.0.1.dist-info/RECORD
dracox-0.0.1.dist-info/WHEEL
dracox-0.0.1.dist-info/METADATA
