Metadata-Version: 2.1
Name: dracox
Version: 0.0.1
Author-Email: Michael Dawson-Haggerty <mikedh@kerfed.com>
Requires-Python: >=3.9
Requires-Dist: numpy
Provides-Extra: test
Requires-Dist: pytest; extra == "test"
Requires-Dist: msgpack; extra == "test"
Requires-Dist: trimesh; extra == "test"
Requires-Dist: lxml; extra == "test"
Requires-Dist: networkx; extra == "test"
Requires-Dist: scipy; extra == "test"
